<annotation verified="yes">
    <folder>Annotation</folder>
    <filename>MY_18670.jpg</filename>
    <path>PBC-PascalVOC-export/Annotations/MY_18670.jpg</path>
    <source>
        <database>Unknown</database>
    </source>
    <size>
        <width>360</width>
        <height>363</height>
        <depth>3</depth>
    </size>
    <segmented>0</segmented>
    <object>
    <name>myelo</name>
    <pose>Unspecified</pose>
    <truncated>0</truncated>
    <difficult>0</difficult>
    <bndbox>
        <xmin>105.51411290322581</xmin>
        <ymin>102.96761446220931</ymin>
        <xmax>262.3419171554252</xmax>
        <ymax>255.62802620821225</ymax>
    </bndbox>
</object>
</annotation>
