<annotation verified="yes">
    <folder>Annotation</folder>
    <filename>PMY_27733.jpg</filename>
    <path>PBC-PascalVOC-export/Annotations/PMY_27733.jpg</path>
    <source>
        <database>Unknown</database>
    </source>
    <size>
        <width>360</width>
        <height>363</height>
        <depth>3</depth>
    </size>
    <segmented>0</segmented>
    <object>
    <name>pro</name>
    <pose>Unspecified</pose>
    <truncated>0</truncated>
    <difficult>0</difficult>
    <bndbox>
        <xmin>100.42109604105572</xmin>
        <ymin>100.01419990007268</ymin>
        <xmax>266.2163214809384</xmax>
        <ymax>270.8176042423692</ymax>
    </bndbox>
</object>
</annotation>
